ripple_counter_dataflow/dff.v
module dff(
	input d,clk,rst,
	output reg q
);
always@(negedge clk or posedge rst) begin
	if (rst==1) q=0;
	else q=d;
end
endmodule

ripple_counter_dataflow/toggle_dff.v
module toggle_dff(
	input clk,rst,
	output q
);
dff dff0(.d(~q),.clk(clk),.rst(rst),.q(q));
endmodule

ripple_counter_dataflow/up_counter.v
module up_counter(
	input clk,rst,
	output [3:0]q
);
toggle_dff tff0(clk,rst,q[0]);
toggle_dff tff1(q[0],rst,q[1]);
toggle_dff tff2(q[1],rst,q[2]);
toggle_dff tff3(q[2],rst,q[3]);
endmodule

ripple_counter_dataflow/up_counter_tb.v
module up_counter_tb();
reg clk,rst; wire [3:0]q;
up_counter dut(.rst(rst),.clk(clk),.q(q));
initial begin
	clk=0;
	forever #5 clk = ~clk;
end
initial begin
	$dumpfile("up_counter_wav.vcd");
	$dumpvars(0,up_counter_tb);
	rst = 0; #1 rst=1; #10 rst=0;
	$monitor("Time=%0t, Q=%b",$time,q);
	#200 $finish;
end
endmodule

ripple_counter_dataflow/up_counter_wav.vcd
$date
	Wed Jun  3 11:35:28 2026
$end
$version
	Icarus Verilog
$end
$timescale
	1s
$end
$scope module up_counter_tb $end
$var wire 4 ! q [3:0] $end
$var reg 1 " clk $end
$var reg 1 # rst $end
$scope module dut $end
$var wire 1 " clk $end
$var wire 1 # rst $end
$var wire 4 $ q [3:0] $end
$scope module tff0 $end
$var wire 1 " clk $end
$var wire 1 # rst $end
$var wire 1 % q $end
$scope module dff0 $end
$var wire 1 " clk $end
$var wire 1 & d $end
$var wire 1 # rst $end
$var reg 1 % q $end
$upscope $end
$upscope $end
$scope module tff1 $end
$var wire 1 ' clk $end
$var wire 1 # rst $end
$var wire 1 ( q $end
$scope module dff0 $end
$var wire 1 ' clk $end
$var wire 1 ) d $end
$var wire 1 # rst $end
$var reg 1 ( q $end
$upscope $end
$upscope $end
$scope module tff2 $end
$var wire 1 * clk $end
$var wire 1 # rst $end
$var wire 1 + q $end
$scope module dff0 $end
$var wire 1 * clk $end
$var wire 1 , d $end
$var wire 1 # rst $end
$var reg 1 + q $end
$upscope $end
$upscope $end
$scope module tff3 $end
$var wire 1 - clk $end
$var wire 1 # rst $end
$var wire 1 . q $end
$scope module dff0 $end
$var wire 1 - clk $end
$var wire 1 / d $end
$var wire 1 # rst $end
$var reg 1 . q $end
$upscope $end
$upscope $end
$upscope $end
$upscope $end
$enddefinitions $end
$comment Show the parameter values. $end
$dumpall
$end
#0
$dumpvars
x/
x.
x-
x,
x+
x*
x)
x(
x'
x&
x%
bx $
0#
0"
bx !
$end
#1
1&
0'
1)
0*
1,
0-
1/
0%
0(
0+
b0 !
b0 $
0.
1#
#5
1"
#10
0"
#11
0#
#15
1"
#20
0&
1'
b1 !
b1 $
1%
0"
#25
1"
#30
0)
1*
1(
1&
0'
b10 !
b10 $
0%
0"
#35
1"
#40
0&
1'
b11 !
b11 $
1%
0"
#45
1"
#50
0,
1-
1+
1)
0*
0(
1&
0'
b100 !
b100 $
0%
0"
#55
1"
#60
0&
1'
b101 !
b101 $
1%
0"
#65
1"
#70
0)
1*
1(
1&
0'
b110 !
b110 $
0%
0"
#75
1"
#80
0&
1'
b111 !
b111 $
1%
0"
#85
1"
#90
0/
1.
1,
0-
0+
1)
0*
0(
1&
0'
b1000 !
b1000 $
0%
0"
#95
1"
#100
0&
1'
b1001 !
b1001 $
1%
0"
#105
1"
#110
0)
1*
1(
1&
0'
b1010 !
b1010 $
0%
0"
#115
1"
#120
0&
1'
b1011 !
b1011 $
1%
0"
#125
1"
#130
0,
1-
1+
1)
0*
0(
1&
0'
b1100 !
b1100 $
0%
0"
#135
1"
#140
0&
1'
b1101 !
b1101 $
1%
0"
#145
1"
#150
0)
1*
1(
1&
0'
b1110 !
b1110 $
0%
0"
#155
1"
#160
0&
1'
b1111 !
b1111 $
1%
0"
#165
1"
#170
1/
0.
1,
0-
0+
1)
0*
0(
1&
0'
b0 !
b0 $
0%
0"
#175
1"
#180
0&
1'
b1 !
b1 $
1%
0"
#185
1"
#190
0)
1*
1(
1&
0'
b10 !
b10 $
0%
0"
#195
1"
#200
0&
1'
b11 !
b11 $
1%
0"
#205
1"
#210
0,
1-
1+
1)
0*
0(
1&
0'
b100 !
b100 $
0%
0"
