0110_overlapping/mealy_0110.v
module mealy_0110(
	input clk, rst, din,
	output reg out
);

parameter s0 = 2'b00;
parameter s1 = 2'b01;
parameter s2 = 2'b10;
parameter s3 = 2'b11;

reg [1:0] present_state;

always @ (posedge clk or posedge rst) begin
	if (rst) begin
		present_state <= s0;
		out <= 1'b0;
	end
	else begin
		case (present_state)
			s0: begin
				if (din) begin
					present_state <= s0;
					out <= 1'b0;
				end
				else begin
					present_state <= s1;
					out <= 1'b0;
				end
			end

			s1: begin
				if (din) begin
					present_state <= s2;
					out <= 1'b0;
				end
				else begin
					present_state <= s1;
					out <= 1'b0;
				end
			end	

			s2: begin
				if (din) begin
					present_state <= s3;
					out <= 1'b0;
				end
				else begin
					present_state <= s1;
					out <= 1'b0;
				end
			end

			s3: begin
				if (din) begin
					present_state <= s0;
					out <= 1'b0;
				end
				else begin
					present_state <= s1;
					out <= 1'b1;
				end
			end
		endcase
	end
end

endmodule

0110_overlapping/mealy_0110_tb.v
module mealy_0110_tb();

reg clk, rst, din;
wire out;

mealy_0110 dut(.clk(clk),.rst(rst),.din(din),.out(out));

initial {clk,rst,din} = 3'b010;
always #5 clk = ~clk;

initial begin
	$dumpfile("mealy_0110_wav.vcd");
	$dumpvars(0,mealy_0110_tb);
	$monitor("Time=%0t, Input = %b, State = %b, Sequence Detected = %b",$time,din,dut.present_state,out);
	#5 rst = 1'b0;
	#10 din = 1'b1;
        #15 din = 1'b0;
	#10 din = 1'b1;
	#20 din = 1'b0;
	#10 din = 1'b1;
	#40 $finish;	
end

endmodule

0110_overlapping/mealy_0110_wav.vcd
$date
	Wed Jun 10 11:10:48 2026
$end
$version
	Icarus Verilog
$end
$timescale
	1s
$end
$scope module mealy_0110_tb $end
$var wire 1 ! out $end
$var reg 1 " clk $end
$var reg 1 # din $end
$var reg 1 $ rst $end
$scope module dut $end
$var wire 1 " clk $end
$var wire 1 # din $end
$var wire 1 $ rst $end
$var parameter 2 % s0 $end
$var parameter 2 & s1 $end
$var parameter 2 ' s2 $end
$var parameter 2 ( s3 $end
$var reg 1 ! out $end
$var reg 2 ) present_state [1:0] $end
$upscope $end
$upscope $end
$enddefinitions $end
$comment Show the parameter values. $end
$dumpall
b11 (
b10 '
b1 &
b0 %
$end
#0
$dumpvars
b0 )
1$
0#
0"
0!
$end
#5
b1 )
0$
1"
#10
0"
#15
b10 )
1"
1#
#20
0"
#25
b11 )
1"
#30
0"
0#
#35
1!
b1 )
1"
#40
0"
1#
#45
0!
b10 )
1"
#50
0"
#55
b11 )
1"
#60
0"
0#
#65
1!
b1 )
1"
#70
0"
1#
#75
0!
b10 )
1"
#80
0"
#85
b11 )
1"
#90
0"
#95
b0 )
1"
