ring_counter/johnson_counter.v
module johnson_counter(
	input clk,rst,
	output reg [3:0] q
);
always@(posedge clk or posedge rst) begin
	if (rst) q = 4'b0000;
	else begin
		q[3] <= q[2];
		q[2] <= q[1];
		q[1] <= q[0];
		q[0] <= ~q[3];
	end
end
endmodule

ring_counter/johnson_counter_tb.v
module johnson_counter_tb();

reg clk,rst;
wire [3:0] q;

johnson_counter dut(.clk(clk),.rst(rst),.q(q));

initial begin
	clk = 1'b1;
	forever #5 clk = ~clk;
end

initial begin
	$dumpfile("johnson_counter_wav.vcd");
	$dumpvars(0,johnson_counter_tb);
	rst = 1'b1;
	#10 rst = 1'b0;
	#100 $finish;
end

endmodule

ring_counter/johnson_counter_wav.vcd
$date
	Sun Jun  7 11:02:40 2026
$end
$version
	Icarus Verilog
$end
$timescale
	1s
$end
$scope module johnson_counter_tb $end
$var wire 4 ! q [3:0] $end
$var reg 1 " clk $end
$var reg 1 # rst $end
$scope module dut $end
$var wire 1 " clk $end
$var wire 1 # rst $end
$var reg 4 $ q [3:0] $end
$upscope $end
$upscope $end
$enddefinitions $end
$comment Show the parameter values. $end
$dumpall
$end
#0
$dumpvars
b0 $
1#
1"
b0 !
$end
#5
0"
#10
b1 !
b1 $
1"
0#
#15
0"
#20
b11 !
b11 $
1"
#25
0"
#30
b111 !
b111 $
1"
#35
0"
#40
b1111 !
b1111 $
1"
#45
0"
#50
b1110 !
b1110 $
1"
#55
0"
#60
b1100 !
b1100 $
1"
#65
0"
#70
b1000 !
b1000 $
1"
#75
0"
#80
b0 !
b0 $
1"
#85
0"
#90
b1 !
b1 $
1"
#95
0"
#100
b11 !
b11 $
1"
#105
0"
#110
b111 !
b111 $
1"
