d_latch/d_latch.v
module d_latch(
	input d,clk,rst,
	output reg q,qbar
);
	always@(*) qbar <= ~q;

	always@(clk or rst or d) begin
		if (rst==1'b1) q = 1'b0;
		else if (clk==1'b1) q = d;
	end
endmodule

d_latch/d_latch_tb.v
module d_latch_tb();
reg d,clk,rst;
wire q,qbar;

d_latch dut(.d(d),.clk(clk),.rst(rst),.q(q),.qbar(qbar));

initial begin
	clk = 1'b0;
	forever #5 clk = ~clk;
end

initial begin
	$dumpfile("d_latch_wav.vcd");
	$dumpvars(0,d_latch_tb);
	$monitor("Time=%0t, D=%b Reset=%b Q=%b Qbar=%b",$time,d,rst,q,qbar);
end

initial begin
	rst = 1'b1; d = 1'b1;
	#10 rst = 1'b0;
	#8 d = 1'b0;
	#2 d = 1'b1;
	#2 d = 1'b0;
	#5 d = 1'b1;
	#10 rst = 1'b1;
	#10 $finish;
end
endmodule

d_latch/d_latch_wav.vcd
$date
	Fri Jun  5 11:54:14 2026
$end
$version
	Icarus Verilog
$end
$timescale
	1s
$end
$scope module d_latch_tb $end
$var wire 1 ! qbar $end
$var wire 1 " q $end
$var reg 1 # clk $end
$var reg 1 $ d $end
$var reg 1 % rst $end
$scope module dut $end
$var wire 1 # clk $end
$var wire 1 $ d $end
$var wire 1 % rst $end
$var reg 1 " q $end
$var reg 1 ! qbar $end
$upscope $end
$upscope $end
$enddefinitions $end
$comment Show the parameter values. $end
$dumpall
$end
#0
$dumpvars
1%
1$
0#
0"
1!
$end
#5
1#
#10
0#
0%
#15
0!
1"
1#
#18
1!
0"
0$
#20
1$
0#
#22
0$
#25
1#
#27
0!
1"
1$
#30
0#
#35
1#
#37
1!
0"
1%
