sequence_detector_110/mealy_110_nov.v
module mealy_110_nov(
	input clk, din, rst,
	output reg detect
);

parameter s0 = 2'b00;
parameter s1 = 2'b01;
parameter s2 = 2'b10;

reg [1:0] ps;


always@(posedge clk or posedge rst) begin
	if(rst) begin
		ps <= s0;
		detect <= 1'b0;
	end
	else begin
		case(ps) 
			s0: begin
				if(din) begin
					ps <= s1;
					detect <= 1'b0;
				end
				else begin
					ps <= s0;
					detect <= 1'b0;
				end
			end

			s1: begin
				if(din) begin
					ps <= s2;
					detect <= 1'b0;
				end
				else begin
					ps <= s0;
					detect <= 1'b0;
				end
			end

			s2: begin
				if(din) begin
					ps <= s1;
					detect <= 1'b0;
				end	
				else begin
					ps <= s0;
					detect <= 1'b1;
				end
			end
		endcase
	end
end

endmodule

sequence_detector_110/mealy_110_nov_tb.v
module mealy_110_nov_tb();

reg clk,rst,din;
wire out;

mealy_110_nov dut(.clk(clk),.rst(rst),.din(din),.detect(out));

initial begin
	{clk,rst,din} = 3'b000;
end

always #5 clk = ~clk;

initial begin
	$dumpfile("mealy_110_nov_wav.vcd");
	$dumpvars(0,mealy_110_nov_tb);
	$monitor("Time=%0t, Input Sequence = %b, Present State = %b, Output (Sequence Detected) = %b",$time,din,dut.ps,out);
	rst = 1'b1; 
	#10 rst = 1'b0; din = 1'b1;
	#40 din = 1'b0;
	#20 $finish;
end

endmodule

sequence_detector_110/mealy_110_nov_wav.vcd
$date
	Tue Jun  9 08:43:10 2026
$end
$version
	Icarus Verilog
$end
$timescale
	1s
$end
$scope module mealy_110_nov_tb $end
$var wire 1 ! out $end
$var reg 1 " clk $end
$var reg 1 # din $end
$var reg 1 $ rst $end
$scope module dut $end
$var wire 1 " clk $end
$var wire 1 # din $end
$var wire 1 $ rst $end
$var parameter 2 % s0 $end
$var parameter 2 & s1 $end
$var parameter 2 ' s2 $end
$var reg 1 ! detect $end
$var reg 2 ( ps [1:0] $end
$upscope $end
$upscope $end
$enddefinitions $end
$comment Show the parameter values. $end
$dumpall
b10 '
b1 &
b0 %
$end
#0
$dumpvars
b0 (
1$
0#
0"
0!
$end
#5
1"
#10
0"
1#
0$
#15
b1 (
1"
#20
0"
#25
b10 (
1"
#30
0"
#35
b1 (
1"
#40
0"
#45
b10 (
1"
#50
0"
0#
#55
1!
b0 (
1"
#60
0"
#65
0!
1"
