sequence_detector_110/moore_110_nov.v
module moore_110_nov(
	input clk, rst, din,
	output reg out
);

parameter s0 = 2'b00;
parameter s1 = 2'b01;
parameter s2 = 2'b10;
parameter s3 = 2'b11;

reg [1:0] present_state;

always @ (posedge clk or posedge rst) begin
	if (rst) begin
		present_state <= s0;
		out <= 1'b0;
	end
	else begin
		case (present_state)
			s0: begin
				out = 1'b0;
				present_state = din ? s1 : s0;
			end

			s1: begin
				out = 1'b0;
				present_state = din ? s2 : s0;
			end

			s2: begin
				out = 1'b0;
				present_state = din ? s2 : s3;
			end

			s3: begin
				out = 1'b1;
				present_state = din ? s1 : s0;
			end
		endcase
	end
end

endmodule

sequence_detector_110/moore_110_nov_tb.v
module moore_110_nov_tb();

reg clk,rst,din;
wire out;

moore_110_nov dut (.clk(clk),.din(din),.rst(rst),.out(out));

initial {clk,rst,din} = 3'b110;
always #5 clk = ~clk;

initial begin
	$dumpfile("moore_110_nov_wav.vcd");
	$dumpvars(0,moore_110_nov_tb);
	$monitor("Time=%0t, Input = %b, Present State = %b, Output (Sequence Detected) = %b",$time,din,dut.present_state,out);
	#5 rst = 1'b0;
	#5 din = 1'b1;
	#30 din = 1'b0;
	#10 din = 1'b1;
	#20 din = 1'b0;
	#20 $finish;
end

endmodule

sequence_detector_110/moore_110_nov_wav.vcd
$date
	Tue Jun  9 10:54:03 2026
$end
$version
	Icarus Verilog
$end
$timescale
	1s
$end
$scope module moore_110_nov_tb $end
$var wire 1 ! out $end
$var reg 1 " clk $end
$var reg 1 # din $end
$var reg 1 $ rst $end
$scope module dut $end
$var wire 1 " clk $end
$var wire 1 # din $end
$var wire 1 $ rst $end
$var parameter 2 % s0 $end
$var parameter 2 & s1 $end
$var parameter 2 ' s2 $end
$var parameter 2 ( s3 $end
$var reg 1 ! out $end
$var reg 2 ) present_state [1:0] $end
$upscope $end
$upscope $end
$enddefinitions $end
$comment Show the parameter values. $end
$dumpall
b11 (
b10 '
b1 &
b0 %
$end
#0
$dumpvars
b0 )
1$
0#
1"
0!
$end
#5
0$
0"
#10
b1 )
1#
1"
#15
0"
#20
b10 )
1"
#25
0"
#30
1"
#35
0"
#40
b11 )
1"
0#
#45
0"
#50
b1 )
1!
1"
1#
#55
0"
#60
b10 )
0!
1"
#65
0"
#70
b11 )
1"
0#
#75
0"
#80
b0 )
1!
1"
#85
0"
#90
0!
1"
