counter/up_down_counter.v
module up_down_counter(
	input up_count,clk,
	output reg [3:0]q
);
initial q = 4'b0000;
always@(posedge clk) begin
	if (up_count) q = q+1;
	else q = q-1;
end	
endmodule

counter/up_down_counter_tb.v
module up_down_counter_tb();

reg clk,up_count;
wire [3:0]q;

up_down_counter dut(.clk(clk),.up_count(up_count),.q(q));

initial begin
	clk = 1'b0;
	forever #5 clk = ~clk;
end

initial begin
	$dumpfile("up_down_counter_wav.vcd");
	$dumpvars(0,up_down_counter_tb);
	$monitor("Time=%0t, Up Count = %b, Q=%d",$time,up_count,q);
	up_count = 1'b1;
	#200 up_count = 1'b0;
	#200 $finish;
end

endmodule

counter/up_down_counter_wav.vcd
$date
	Sat Jun  6 12:46:37 2026
$end
$version
	Icarus Verilog
$end
$timescale
	1s
$end
$scope module up_down_counter_tb $end
$var wire 4 ! q [3:0] $end
$var reg 1 " clk $end
$var reg 1 # up_count $end
$scope module dut $end
$var wire 1 " clk $end
$var wire 1 # up_count $end
$var reg 4 $ q [3:0] $end
$upscope $end
$upscope $end
$enddefinitions $end
$comment Show the parameter values. $end
$dumpall
$end
#0
$dumpvars
b0 $
1#
0"
b0 !
$end
#5
b1 !
b1 $
1"
#10
0"
#15
b10 !
b10 $
1"
#20
0"
#25
b11 !
b11 $
1"
#30
0"
#35
b100 !
b100 $
1"
#40
0"
#45
b101 !
b101 $
1"
#50
0"
#55
b110 !
b110 $
1"
#60
0"
#65
b111 !
b111 $
1"
#70
0"
#75
b1000 !
b1000 $
1"
#80
0"
#85
b1001 !
b1001 $
1"
#90
0"
#95
b1010 !
b1010 $
1"
#100
0"
#105
b1011 !
b1011 $
1"
#110
0"
#115
b1100 !
b1100 $
1"
#120
0"
#125
b1101 !
b1101 $
1"
#130
0"
#135
b1110 !
b1110 $
1"
#140
0"
#145
b1111 !
b1111 $
1"
#150
0"
#155
b0 !
b0 $
1"
#160
0"
#165
b1 !
b1 $
1"
#170
0"
#175
b10 !
b10 $
1"
#180
0"
#185
b11 !
b11 $
1"
#190
0"
#195
b100 !
b100 $
1"
#200
0"
0#
#205
b11 !
b11 $
1"
#210
0"
#215
b10 !
b10 $
1"
#220
0"
#225
b1 !
b1 $
1"
#230
0"
#235
b0 !
b0 $
1"
#240
0"
#245
b1111 !
b1111 $
1"
#250
0"
#255
b1110 !
b1110 $
1"
#260
0"
#265
b1101 !
b1101 $
1"
#270
0"
#275
b1100 !
b1100 $
1"
#280
0"
#285
b1011 !
b1011 $
1"
#290
0"
#295
b1010 !
b1010 $
1"
#300
0"
#305
b1001 !
b1001 $
1"
#310
0"
#315
b1000 !
b1000 $
1"
#320
0"
#325
b111 !
b111 $
1"
#330
0"
#335
b110 !
b110 $
1"
#340
0"
#345
b101 !
b101 $
1"
#350
0"
#355
b100 !
b100 $
1"
#360
0"
#365
b11 !
b11 $
1"
#370
0"
#375
b10 !
b10 $
1"
#380
0"
#385
b1 !
b1 $
1"
#390
0"
#395
b0 !
b0 $
1"
