universal_shift_register/universal_shift_register.v
module universal_shift_register(
	input [1:0] mode,
	input [0:3] parallel_in,
	input serial_in_right, serial_in_left,
	input rst,clk,
	output reg [0:3] q,
	output reg serial_out_right, serial_out_left
);

always @ (*) begin
	serial_out_right = q[3];
	serial_out_left = q[0];
end

always @ (posedge clk or negedge rst) begin
	if (!rst)
		q <= 4'b0000;

	else begin
		case(mode)
			2'b00: q <= q; // No change
			2'b01: q <= {serial_in_right,q[0:2]}; // Shift Right
			2'b10: q <= {q[1:3],serial_in_left}; // Shift Left
			2'b11: q <= parallel_in;
		endcase
	end
end

endmodule

universal_shift_register/tb_universal_shift_register.v
`timescale 1ns/1ps

module universal_shift_register_tb();

reg clk, rst, serial_in_right, serial_in_left;
reg [0:3] parallel_in;
reg [1:0] mode;
wire [0:3] parallel_out;
wire serial_out_right, serial_out_left;

universal_shift_register dut (.clk(clk), .rst(rst), .serial_in_right(serial_in_right), .serial_in_left(serial_in_left),
	.parallel_in(parallel_in), .mode(mode), .q(parallel_out),
	.serial_out_right(serial_out_right), .serial_out_left(serial_out_left));

initial {clk, rst, serial_in_right, serial_in_left} = 4'b0000;

always #5 clk = ~clk;

initial begin
	$dumpfile("wav_universal_shift_register.vcd");
	$dumpvars(0,universal_shift_register_tb);
	#5 rst = 1'b1;
	mode = 2'b11; parallel_in = 4'b1101;
	#15 mode = 2'b01;
	#10 mode = 2'b10;
	#10 mode = 2'b11; parallel_in = 4'b0011;
	#20 $finish;
end

endmodule

universal_shift_register/wav_universal_shift_register.vcd
$date
	Wed Jun 24 10:57:15 2026
$end
$version
	Icarus Verilog
$end
$timescale
	1ps
$end
$scope module universal_shift_register_tb $end
$var wire 1 ! serial_out_right $end
$var wire 1 " serial_out_left $end
$var wire 4 # parallel_out [0:3] $end
$var reg 1 $ clk $end
$var reg 2 % mode [1:0] $end
$var reg 4 & parallel_in [0:3] $end
$var reg 1 ' rst $end
$var reg 1 ( serial_in_left $end
$var reg 1 ) serial_in_right $end
$scope module dut $end
$var wire 1 $ clk $end
$var wire 2 * mode [1:0] $end
$var wire 4 + parallel_in [0:3] $end
$var wire 1 ' rst $end
$var wire 1 ( serial_in_left $end
$var wire 1 ) serial_in_right $end
$var reg 4 , q [0:3] $end
$var reg 1 " serial_out_left $end
$var reg 1 ! serial_out_right $end
$upscope $end
$upscope $end
$enddefinitions $end
$comment Show the parameter values. $end
$dumpall
$end
#0
$dumpvars
b0 ,
bx +
bx *
0)
0(
0'
bx &
bx %
0$
b0 #
0"
0!
$end
#5000
1"
1!
b1101 #
b1101 ,
b1101 &
b1101 +
b11 %
b11 *
1'
1$
#10000
0$
#15000
1$
#20000
0$
b1 %
b1 *
#25000
0"
0!
b110 #
b110 ,
1$
#30000
0$
b10 %
b10 *
#35000
1"
b1100 #
b1100 ,
1$
#40000
0$
b11 &
b11 +
b11 %
b11 *
#45000
0"
1!
b11 #
b11 ,
1$
